dilemma/__init__.py
dilemma/arraymethods.py
dilemma/dates.py
dilemma/lang.py
dilemma/logconf.py
dilemma/utils.py
dilemma/version.py
dilemma/errors/__init__.py
dilemma/errors/examples.py
dilemma/errors/exc.py
dilemma/errors/execution.py
dilemma/errors/messages.py
dilemma/errors/msg_templates.xml
dilemma/errors/parsing.py
dilemma/ext/__init__.py
dilemma/ext/async.py
dilemma/ext/builder.py
dilemma/ext/cli.py
dilemma/ext/humanise.py
dilemma/ext/typecheck.py
dilemma/ext/url_resolver.py
dilemma/resolvers/__init__.py
dilemma/resolvers/basic_resolver.py
dilemma/resolvers/interface.py
dilemma/resolvers/jq_resolver.py
dilemma/resolvers/jsonpath_resolver.py
dilemma-0.6.2.dist-info/licenses/LICENSE
dilemma-0.6.2.dist-info/METADATA
dilemma-0.6.2.dist-info/WHEEL
dilemma-0.6.2.dist-info/entry_points.txt
dilemma-0.6.2.dist-info/top_level.txt
dilemma-0.6.2.dist-info/RECORD
