Metadata-Version: 2.4
Name: dilemma
Version: 0.6.2
Summary: This is an expression language python package.
Author-email: Patrick Dobbs <patrick.dobbs@gmail.com>
License-Expression: MIT
Project-URL: Homepage, https://github.com/patrickcd/dilemma
Project-URL: Repository, https://github.com/patrickcd/dilemma.git
Project-URL: Issues, https://github.com/patrickcd/dilemma/issues
Platform: unix
Platform: linux
Platform: osx
Platform: cygwin
Platform: win32
Classifier: Programming Language :: Python :: 3
Classifier: Programming Language :: Python :: 3.12
Classifier: Programming Language :: Python :: 3.13
Classifier: Operating System :: Microsoft :: Windows
Classifier: Operating System :: POSIX :: Linux
Classifier: Operating System :: POSIX
Classifier: Operating System :: Unix
Classifier: Operating System :: MacOS
Requires-Python: >=3.12
License-File: LICENSE
Requires-Dist: lark
Requires-Dist: jq
Requires-Dist: click
Requires-Dist: pyyaml
Requires-Dist: jsonpath-ng>=1.7.0
Requires-Dist: validate-pyproject>=0.24.1
Requires-Dist: packaging>=25.0
Provides-Extra: test
Requires-Dist: pytest; extra == "test"
Requires-Dist: pytest-cov; extra == "test"
Requires-Dist: codecov; extra == "test"
Requires-Dist: coverage[toml]; extra == "test"
Requires-Dist: pre-commit; extra == "test"
Requires-Dist: pyyaml; extra == "test"
Requires-Dist: hypothesis>=6.136.4; extra == "test"
Provides-Extra: doc
Requires-Dist: mkdocs; extra == "doc"
Requires-Dist: mkdocstrings; extra == "doc"
Requires-Dist: mkdocstrings[python]; extra == "doc"
Requires-Dist: mkdocs-material; extra == "doc"
Requires-Dist: Pygments; extra == "doc"
Provides-Extra: dev
Requires-Dist: click; extra == "dev"
Requires-Dist: isort; extra == "dev"
Requires-Dist: mypy; extra == "dev"
Requires-Dist: pre-commit; extra == "dev"
Requires-Dist: ruff; extra == "dev"
Requires-Dist: types-PyYAML; extra == "dev"
Provides-Extra: all
Requires-Dist: dilemma[dev,doc,test]; extra == "all"
Dynamic: license-file
